nbsnapshot/__init__.py
nbsnapshot/cli.py
nbsnapshot/compare.py
nbsnapshot/exceptions.py
nbsnapshot-0.2.2.dist-info/LICENSE
nbsnapshot-0.2.2.dist-info/METADATA
nbsnapshot-0.2.2.dist-info/WHEEL
nbsnapshot-0.2.2.dist-info/entry_points.txt
nbsnapshot-0.2.2.dist-info/top_level.txt
nbsnapshot-0.2.2.dist-info/RECORD
