Metadata-Version: 2.1
Name: nbsnapshot
Version: 0.2.2
License-File: LICENSE
Requires-Dist: click
Requires-Dist: papermill
Requires-Dist: ploomber-core (>=0.0.4)
Requires-Dist: ipykernel
Requires-Dist: sklearn-evaluation
Provides-Extra: dev
Requires-Dist: pytest ; extra == 'dev'
Requires-Dist: flake8 ; extra == 'dev'
Requires-Dist: nbformat ; extra == 'dev'
Requires-Dist: ipykernel ; extra == 'dev'
Requires-Dist: invoke ; extra == 'dev'
